<?xml version="1.0" encoding="utf-8"?>
<Document>
  <Engineering version="V18" />
  <SW.Types.PlcStruct ID="0">
    <AttributeList>
      <Interface><Sections xmlns="http://www.siemens.com/automation/Openness/SW/Interface/v5">
  <Section Name="None">
    <Member Name="BUZZER" Datatype="Bool">
      <AttributeList>
        <BooleanAttribute Name="ExternalAccessible" SystemDefined="true">true</BooleanAttribute>
        <BooleanAttribute Name="ExternalVisible" SystemDefined="true">true</BooleanAttribute>
        <BooleanAttribute Name="ExternalWritable" SystemDefined="true">true</BooleanAttribute>
        <BooleanAttribute Name="SetPoint" SystemDefined="true">false</BooleanAttribute>
      </AttributeList>
    </Member>
    <Member Name="BFV 1" Datatype="Bool">
      <AttributeList>
        <BooleanAttribute Name="ExternalAccessible" SystemDefined="true">true</BooleanAttribute>
        <BooleanAttribute Name="ExternalVisible" SystemDefined="true">true</BooleanAttribute>
        <BooleanAttribute Name="ExternalWritable" SystemDefined="true">true</BooleanAttribute>
        <BooleanAttribute Name="SetPoint" SystemDefined="true">false</BooleanAttribute>
      </AttributeList>
    </Member>
    <Member Name="BFV 2" Datatype="Bool">
      <AttributeList>
        <BooleanAttribute Name="ExternalAccessible" SystemDefined="true">true</BooleanAttribute>
        <BooleanAttribute Name="ExternalVisible" SystemDefined="true">true</BooleanAttribute>
        <BooleanAttribute Name="ExternalWritable" SystemDefined="true">true</BooleanAttribute>
        <BooleanAttribute Name="SetPoint" SystemDefined="true">false</BooleanAttribute>
      </AttributeList>
    </Member>
    <Member Name="BFV 3" Datatype="Bool">
      <AttributeList>
        <BooleanAttribute Name="ExternalAccessible" SystemDefined="true">true</BooleanAttribute>
        <BooleanAttribute Name="ExternalVisible" SystemDefined="true">true</BooleanAttribute>
        <BooleanAttribute Name="ExternalWritable" SystemDefined="true">true</BooleanAttribute>
        <BooleanAttribute Name="SetPoint" SystemDefined="true">false</BooleanAttribute>
      </AttributeList>
    </Member>
    <Member Name="BFV 4" Datatype="Bool">
      <AttributeList>
        <BooleanAttribute Name="ExternalAccessible" SystemDefined="true">true</BooleanAttribute>
        <BooleanAttribute Name="ExternalVisible" SystemDefined="true">true</BooleanAttribute>
        <BooleanAttribute Name="ExternalWritable" SystemDefined="true">true</BooleanAttribute>
        <BooleanAttribute Name="SetPoint" SystemDefined="true">false</BooleanAttribute>
      </AttributeList>
    </Member>
    <Member Name="BFV 5" Datatype="Bool">
      <AttributeList>
        <BooleanAttribute Name="ExternalAccessible" SystemDefined="true">true</BooleanAttribute>
        <BooleanAttribute Name="ExternalVisible" SystemDefined="true">true</BooleanAttribute>
        <BooleanAttribute Name="ExternalWritable" SystemDefined="true">true</BooleanAttribute>
        <BooleanAttribute Name="SetPoint" SystemDefined="true">false</BooleanAttribute>
      </AttributeList>
    </Member>
    <Member Name="BFV 6" Datatype="Bool">
      <AttributeList>
        <BooleanAttribute Name="ExternalAccessible" SystemDefined="true">true</BooleanAttribute>
        <BooleanAttribute Name="ExternalVisible" SystemDefined="true">true</BooleanAttribute>
        <BooleanAttribute Name="ExternalWritable" SystemDefined="true">true</BooleanAttribute>
        <BooleanAttribute Name="SetPoint" SystemDefined="true">false</BooleanAttribute>
      </AttributeList>
    </Member>
    <Member Name="BFV 7" Datatype="Bool">
      <AttributeList>
        <BooleanAttribute Name="ExternalAccessible" SystemDefined="true">true</BooleanAttribute>
        <BooleanAttribute Name="ExternalVisible" SystemDefined="true">true</BooleanAttribute>
        <BooleanAttribute Name="ExternalWritable" SystemDefined="true">true</BooleanAttribute>
        <BooleanAttribute Name="SetPoint" SystemDefined="true">false</BooleanAttribute>
      </AttributeList>
    </Member>
    <Member Name="BFV 8" Datatype="Bool">
      <AttributeList>
        <BooleanAttribute Name="ExternalAccessible" SystemDefined="true">true</BooleanAttribute>
        <BooleanAttribute Name="ExternalVisible" SystemDefined="true">true</BooleanAttribute>
        <BooleanAttribute Name="ExternalWritable" SystemDefined="true">true</BooleanAttribute>
        <BooleanAttribute Name="SetPoint" SystemDefined="true">false</BooleanAttribute>
      </AttributeList>
    </Member>
    <Member Name="BFV 9" Datatype="Bool">
      <AttributeList>
        <BooleanAttribute Name="ExternalAccessible" SystemDefined="true">true</BooleanAttribute>
        <BooleanAttribute Name="ExternalVisible" SystemDefined="true">true</BooleanAttribute>
        <BooleanAttribute Name="ExternalWritable" SystemDefined="true">true</BooleanAttribute>
        <BooleanAttribute Name="SetPoint" SystemDefined="true">false</BooleanAttribute>
      </AttributeList>
    </Member>
    <Member Name="R1" Datatype="Bool">
      <AttributeList>
        <BooleanAttribute Name="ExternalAccessible" SystemDefined="true">true</BooleanAttribute>
        <BooleanAttribute Name="ExternalVisible" SystemDefined="true">true</BooleanAttribute>
        <BooleanAttribute Name="ExternalWritable" SystemDefined="true">true</BooleanAttribute>
        <BooleanAttribute Name="SetPoint" SystemDefined="true">false</BooleanAttribute>
      </AttributeList>
    </Member>
    <Member Name="R2" Datatype="Bool">
      <AttributeList>
        <BooleanAttribute Name="ExternalAccessible" SystemDefined="true">true</BooleanAttribute>
        <BooleanAttribute Name="ExternalVisible" SystemDefined="true">true</BooleanAttribute>
        <BooleanAttribute Name="ExternalWritable" SystemDefined="true">true</BooleanAttribute>
        <BooleanAttribute Name="SetPoint" SystemDefined="true">false</BooleanAttribute>
      </AttributeList>
    </Member>
    <Member Name="R3" Datatype="Bool">
      <AttributeList>
        <BooleanAttribute Name="ExternalAccessible" SystemDefined="true">true</BooleanAttribute>
        <BooleanAttribute Name="ExternalVisible" SystemDefined="true">true</BooleanAttribute>
        <BooleanAttribute Name="ExternalWritable" SystemDefined="true">true</BooleanAttribute>
        <BooleanAttribute Name="SetPoint" SystemDefined="true">false</BooleanAttribute>
      </AttributeList>
    </Member>
    <Member Name="R4" Datatype="Bool">
      <AttributeList>
        <BooleanAttribute Name="ExternalAccessible" SystemDefined="true">true</BooleanAttribute>
        <BooleanAttribute Name="ExternalVisible" SystemDefined="true">true</BooleanAttribute>
        <BooleanAttribute Name="ExternalWritable" SystemDefined="true">true</BooleanAttribute>
        <BooleanAttribute Name="SetPoint" SystemDefined="true">false</BooleanAttribute>
      </AttributeList>
    </Member>
    <Member Name="R5" Datatype="Bool">
      <AttributeList>
        <BooleanAttribute Name="ExternalAccessible" SystemDefined="true">true</BooleanAttribute>
        <BooleanAttribute Name="ExternalVisible" SystemDefined="true">true</BooleanAttribute>
        <BooleanAttribute Name="ExternalWritable" SystemDefined="true">true</BooleanAttribute>
        <BooleanAttribute Name="SetPoint" SystemDefined="true">false</BooleanAttribute>
      </AttributeList>
    </Member>
    <Member Name="R6" Datatype="Bool">
      <AttributeList>
        <BooleanAttribute Name="ExternalAccessible" SystemDefined="true">true</BooleanAttribute>
        <BooleanAttribute Name="ExternalVisible" SystemDefined="true">true</BooleanAttribute>
        <BooleanAttribute Name="ExternalWritable" SystemDefined="true">true</BooleanAttribute>
        <BooleanAttribute Name="SetPoint" SystemDefined="true">false</BooleanAttribute>
      </AttributeList>
    </Member>
    <Member Name="BFV 10" Datatype="Bool">
      <AttributeList>
        <BooleanAttribute Name="ExternalAccessible" SystemDefined="true">true</BooleanAttribute>
        <BooleanAttribute Name="ExternalVisible" SystemDefined="true">true</BooleanAttribute>
        <BooleanAttribute Name="ExternalWritable" SystemDefined="true">true</BooleanAttribute>
        <BooleanAttribute Name="SetPoint" SystemDefined="true">false</BooleanAttribute>
      </AttributeList>
    </Member>
    <Member Name="BFV 11" Datatype="Bool">
      <AttributeList>
        <BooleanAttribute Name="ExternalAccessible" SystemDefined="true">true</BooleanAttribute>
        <BooleanAttribute Name="ExternalVisible" SystemDefined="true">true</BooleanAttribute>
        <BooleanAttribute Name="ExternalWritable" SystemDefined="true">true</BooleanAttribute>
        <BooleanAttribute Name="SetPoint" SystemDefined="true">false</BooleanAttribute>
      </AttributeList>
    </Member>
    <Member Name="BFV 12" Datatype="Bool">
      <AttributeList>
        <BooleanAttribute Name="ExternalAccessible" SystemDefined="true">true</BooleanAttribute>
        <BooleanAttribute Name="ExternalVisible" SystemDefined="true">true</BooleanAttribute>
        <BooleanAttribute Name="ExternalWritable" SystemDefined="true">true</BooleanAttribute>
        <BooleanAttribute Name="SetPoint" SystemDefined="true">false</BooleanAttribute>
      </AttributeList>
    </Member>
    <Member Name="BFV 13" Datatype="Bool">
      <AttributeList>
        <BooleanAttribute Name="ExternalAccessible" SystemDefined="true">true</BooleanAttribute>
        <BooleanAttribute Name="ExternalVisible" SystemDefined="true">true</BooleanAttribute>
        <BooleanAttribute Name="ExternalWritable" SystemDefined="true">true</BooleanAttribute>
        <BooleanAttribute Name="SetPoint" SystemDefined="true">false</BooleanAttribute>
      </AttributeList>
    </Member>
    <Member Name="BFV 14" Datatype="Bool">
      <AttributeList>
        <BooleanAttribute Name="ExternalAccessible" SystemDefined="true">true</BooleanAttribute>
        <BooleanAttribute Name="ExternalVisible" SystemDefined="true">true</BooleanAttribute>
        <BooleanAttribute Name="ExternalWritable" SystemDefined="true">true</BooleanAttribute>
        <BooleanAttribute Name="SetPoint" SystemDefined="true">false</BooleanAttribute>
      </AttributeList>
    </Member>
    <Member Name="BFV 15" Datatype="Bool">
      <AttributeList>
        <BooleanAttribute Name="ExternalAccessible" SystemDefined="true">true</BooleanAttribute>
        <BooleanAttribute Name="ExternalVisible" SystemDefined="true">true</BooleanAttribute>
        <BooleanAttribute Name="ExternalWritable" SystemDefined="true">true</BooleanAttribute>
        <BooleanAttribute Name="SetPoint" SystemDefined="true">false</BooleanAttribute>
      </AttributeList>
    </Member>
    <Member Name="BFV 16" Datatype="Bool">
      <AttributeList>
        <BooleanAttribute Name="ExternalAccessible" SystemDefined="true">true</BooleanAttribute>
        <BooleanAttribute Name="ExternalVisible" SystemDefined="true">true</BooleanAttribute>
        <BooleanAttribute Name="ExternalWritable" SystemDefined="true">true</BooleanAttribute>
        <BooleanAttribute Name="SetPoint" SystemDefined="true">false</BooleanAttribute>
      </AttributeList>
    </Member>
    <Member Name="BFV 17" Datatype="Bool">
      <AttributeList>
        <BooleanAttribute Name="ExternalAccessible" SystemDefined="true">true</BooleanAttribute>
        <BooleanAttribute Name="ExternalVisible" SystemDefined="true">true</BooleanAttribute>
        <BooleanAttribute Name="ExternalWritable" SystemDefined="true">true</BooleanAttribute>
        <BooleanAttribute Name="SetPoint" SystemDefined="true">false</BooleanAttribute>
      </AttributeList>
    </Member>
    <Member Name="BFV 18" Datatype="Bool">
      <AttributeList>
        <BooleanAttribute Name="ExternalAccessible" SystemDefined="true">true</BooleanAttribute>
        <BooleanAttribute Name="ExternalVisible" SystemDefined="true">true</BooleanAttribute>
        <BooleanAttribute Name="ExternalWritable" SystemDefined="true">true</BooleanAttribute>
        <BooleanAttribute Name="SetPoint" SystemDefined="true">false</BooleanAttribute>
      </AttributeList>
    </Member>
    <Member Name="BFV 19" Datatype="Bool">
      <AttributeList>
        <BooleanAttribute Name="ExternalAccessible" SystemDefined="true">true</BooleanAttribute>
        <BooleanAttribute Name="ExternalVisible" SystemDefined="true">true</BooleanAttribute>
        <BooleanAttribute Name="ExternalWritable" SystemDefined="true">true</BooleanAttribute>
        <BooleanAttribute Name="SetPoint" SystemDefined="true">false</BooleanAttribute>
      </AttributeList>
    </Member>
    <Member Name="CIP SUPPLY PUMP START (VFD)" Datatype="Bool">
      <AttributeList>
        <BooleanAttribute Name="ExternalAccessible" SystemDefined="true">true</BooleanAttribute>
        <BooleanAttribute Name="ExternalVisible" SystemDefined="true">true</BooleanAttribute>
        <BooleanAttribute Name="ExternalWritable" SystemDefined="true">true</BooleanAttribute>
        <BooleanAttribute Name="SetPoint" SystemDefined="true">false</BooleanAttribute>
      </AttributeList>
    </Member>
    <Member Name="ACID DOSING PUMP" Datatype="Bool">
      <AttributeList>
        <BooleanAttribute Name="ExternalAccessible" SystemDefined="true">true</BooleanAttribute>
        <BooleanAttribute Name="ExternalVisible" SystemDefined="true">true</BooleanAttribute>
        <BooleanAttribute Name="ExternalWritable" SystemDefined="true">true</BooleanAttribute>
        <BooleanAttribute Name="SetPoint" SystemDefined="true">false</BooleanAttribute>
      </AttributeList>
    </Member>
    <Member Name="CAUSTIC DOSING PUMP" Datatype="Bool">
      <AttributeList>
        <BooleanAttribute Name="ExternalAccessible" SystemDefined="true">true</BooleanAttribute>
        <BooleanAttribute Name="ExternalVisible" SystemDefined="true">true</BooleanAttribute>
        <BooleanAttribute Name="ExternalWritable" SystemDefined="true">true</BooleanAttribute>
        <BooleanAttribute Name="SetPoint" SystemDefined="true">false</BooleanAttribute>
      </AttributeList>
    </Member>
    <Member Name="RETURN PUMP 1" Datatype="Bool">
      <AttributeList>
        <BooleanAttribute Name="ExternalAccessible" SystemDefined="true">true</BooleanAttribute>
        <BooleanAttribute Name="ExternalVisible" SystemDefined="true">true</BooleanAttribute>
        <BooleanAttribute Name="ExternalWritable" SystemDefined="true">true</BooleanAttribute>
        <BooleanAttribute Name="SetPoint" SystemDefined="true">false</BooleanAttribute>
      </AttributeList>
    </Member>
    <Member Name="RETURN PUMP 2" Datatype="Bool">
      <AttributeList>
        <BooleanAttribute Name="ExternalAccessible" SystemDefined="true">true</BooleanAttribute>
        <BooleanAttribute Name="ExternalVisible" SystemDefined="true">true</BooleanAttribute>
        <BooleanAttribute Name="ExternalWritable" SystemDefined="true">true</BooleanAttribute>
        <BooleanAttribute Name="SetPoint" SystemDefined="true">false</BooleanAttribute>
      </AttributeList>
    </Member>
    <Member Name="RETUEN PUMP 3" Datatype="Bool">
      <AttributeList>
        <BooleanAttribute Name="ExternalAccessible" SystemDefined="true">true</BooleanAttribute>
        <BooleanAttribute Name="ExternalVisible" SystemDefined="true">true</BooleanAttribute>
        <BooleanAttribute Name="ExternalWritable" SystemDefined="true">true</BooleanAttribute>
        <BooleanAttribute Name="SetPoint" SystemDefined="true">false</BooleanAttribute>
      </AttributeList>
    </Member>
  </Section>
</Sections></Interface>
      <IsFailsafeCompliant>false</IsFailsafeCompliant>
      <Name>DO</Name>
      <Namespace />
    </AttributeList>
    <ObjectList>
      <MultilingualText ID="1" CompositionName="Comment">
        <ObjectList>
          <MultilingualTextItem ID="2" CompositionName="Items">
            <AttributeList>
              <Culture>en-US</Culture>
              <Text />
            </AttributeList>
          </MultilingualTextItem>
        </ObjectList>
      </MultilingualText>
      <MultilingualText ID="3" CompositionName="Title">
        <ObjectList>
          <MultilingualTextItem ID="4" CompositionName="Items">
            <AttributeList>
              <Culture>en-US</Culture>
              <Text />
            </AttributeList>
          </MultilingualTextItem>
        </ObjectList>
      </MultilingualText>
    </ObjectList>
  </SW.Types.PlcStruct>
</Document>